arbiterd/__init__.py
arbiterd/dispatcher.py
arbiterd/arbiters/__init__.py
arbiterd/arbiters/base.py
arbiterd/arbiters/cpu_state.py
arbiterd/cmd/__init__.py
arbiterd/cmd/static.py
arbiterd/common/__init__.py
arbiterd/common/cpu.py
arbiterd/common/filesystem.py
arbiterd/common/libvirt.py
arbiterd/common/nova.py
arbiterd/conf/__init__.py
arbiterd/objects/__init__.py
arbiterd/objects/context.py
arbiterd/objects/hardware_thread.py
arbiterd/objects/instance.py
arbiterd-0.0.7.dist-info/LICENSE.txt
arbiterd-0.0.7.dist-info/METADATA
arbiterd-0.0.7.dist-info/WHEEL
arbiterd-0.0.7.dist-info/entry_points.txt
arbiterd-0.0.7.dist-info/top_level.txt
arbiterd-0.0.7.dist-info/RECORD
