Metadata-Version: 2.1
Name: arbiterd
Version: 0.0.7
Summary: A collection of daemons to arbitrate power and performance
Home-page: https://github.com/SeanMooney/arbiterd
Author: Sean Mooney
Author-email: work@seanmooney.info
License: Apache-2.0
Project-URL: Documentation, https://github.com/SeanMooney/arbiterd
Project-URL: Source, https://github.com/SeanMooney/arbiterd
Project-URL: Tracker, https://github.com/SeanMooney/arbiterd/issues
Project-URL: Download, https://pypi.org/project/arbiterd/#files
Platform: Linux
Classifier: Development Status :: 2 - Pre-Alpha
Classifier: Programming Language :: Python
Classifier: Programming Language :: Python :: 3 :: Only
Classifier: Programming Language :: Python :: 3.6
Classifier: Programming Language :: Python :: 3.8
Classifier: Programming Language :: Python :: 3.9
Classifier: Programming Language :: Python :: 3.10
Classifier: Programming Language :: Python :: Implementation :: CPython
Classifier: License :: OSI Approved :: Apache Software License
Requires-Python: >=3.6
License-File: LICENSE.txt
Requires-Dist: libvirt-python
Requires-Dist: defusedxml
Requires-Dist: dataclasses ; python_version < "3.7"
Requires-Dist: importlib-metadata ; python_version < "3.8"
Provides-Extra: testing
Requires-Dist: setuptools ; extra == 'testing'
Requires-Dist: pytest ; extra == 'testing'
Requires-Dist: pytest-cov ; extra == 'testing'
Requires-Dist: fixtures ; extra == 'testing'
Requires-Dist: testtools ; extra == 'testing'
Requires-Dist: pytest-xdist ; extra == 'testing'
